sentianaylib/__init__.py
sentianaylib/dataprocessor.py
sentianaylib/setup.py
sentianaylib-1.0.2.dist-info/LICENSE
sentianaylib-1.0.2.dist-info/METADATA
sentianaylib-1.0.2.dist-info/WHEEL
sentianaylib-1.0.2.dist-info/top_level.txt
sentianaylib-1.0.2.dist-info/RECORD
