Metadata-Version: 2.1
Name: sentianaylib
Version: 1.0.2
Summary: A Python package for sentiment analysis
Home-page: https://github.com/chameleonlabs2021/sentianaylib
Author-email: chameleonlabs2021@gmail.com
License-File: LICENSE
Requires-Dist: beautifulsoup4 >=4.12.3
Requires-Dist: textblob >=0.18.0
Requires-Dist: selenium >=4.18.1
Requires-Dist: webdriver-manager >=4.0.1
